universal_analytics/__init__.py
universal_analytics/requests.py
universal_analytics/tracker.py
universal_analytics_python3-1.1.1.dist-info/LICENSE
universal_analytics_python3-1.1.1.dist-info/METADATA
universal_analytics_python3-1.1.1.dist-info/WHEEL
universal_analytics_python3-1.1.1.dist-info/top_level.txt
universal_analytics_python3-1.1.1.dist-info/RECORD
