Metadata-Version: 2.1
Name: universal-analytics-python3
Version: 1.1.1
Summary: Universal analytics python library
Home-page: https://github.com/dmvass/universal-analytics-python3
Author: Dmitri Vasilishin
Author-email: vasilishin.d.o@gmail.com
License: UNKNOWN
Keywords: python,analytics,google-analytics
Platform: UNKNOWN
Classifier: Development Status :: 5 - Production/Stable
Classifier: Intended Audience :: Developers
Classifier: Programming Language :: Python :: 3
Classifier: Programming Language :: Python :: 3.7
Classifier: Programming Language :: Python :: 3.8
Classifier: Programming Language :: Python :: 3.9
Classifier: License :: OSI Approved :: MIT License
Classifier: Operating System :: OS Independent
